LICENSE
README.md
setup.py
jsonschema_inference/__init__.py
jsonschema_inference/config.py
jsonschema_inference/version.py
jsonschema_inference.egg-info/PKG-INFO
jsonschema_inference.egg-info/SOURCES.txt
jsonschema_inference.egg-info/dependency_links.txt
jsonschema_inference.egg-info/entry_points.txt
jsonschema_inference.egg-info/requires.txt
jsonschema_inference.egg-info/top_level.txt
jsonschema_inference/cmd/__init__.py
jsonschema_inference/cmd/inference.py
jsonschema_inference/inference/__init__.py
jsonschema_inference/inference/api.py
jsonschema_inference/inference/jsonl.py
jsonschema_inference/inference/remote.py
jsonschema_inference/schema/__init__.py
jsonschema_inference/schema/fitter.py
jsonschema_inference/schema/inference/__init__.py
jsonschema_inference/schema/inference/base.py
jsonschema_inference/schema/inference/reduce.py
jsonschema_inference/schema/objs/__init__.py
jsonschema_inference/schema/objs/array.py
jsonschema_inference/schema/objs/basic.py
jsonschema_inference/schema/objs/records.py